textfun/__init__.py
textfun/funciones.py
textfun-0.1.2.dist-info/licenses/LICENSE
textfun-0.1.2.dist-info/METADATA
textfun-0.1.2.dist-info/WHEEL
textfun-0.1.2.dist-info/top_level.txt
textfun-0.1.2.dist-info/RECORD
