Metadata-Version: 2.4
Name: textfun
Version: 0.1.2
Summary: Librería educativa para jugar con texto: invertir, contar vocales, alternar mayúsculas, etc.
Author: Enrique Duque
License: MIT
Project-URL: Homepage, https://pypi.org/project/textfun/
Classifier: Programming Language :: Python :: 3
Classifier: License :: OSI Approved :: MIT License
Classifier: Operating System :: OS Independent
Requires-Python: >=3.8
License-File: LICENSE
Dynamic: license-file
